quiz/QUESTIONS.toml
quiz/__init__.py
quiz/add_question.py
quiz/quiz.py
squaz-0.1.2.dist-info/LICENSE
squaz-0.1.2.dist-info/METADATA
squaz-0.1.2.dist-info/WHEEL
squaz-0.1.2.dist-info/RECORD
