Metadata-Version: 2.1
Name: squaz
Version: 0.1.2
Summary: An app to quiz the user on trivia
Author: Robert Portelli
Author-email: github@robertportelli.com
Requires-Python: >=3.11,<4.0
Classifier: Programming Language :: Python :: 3
Classifier: Programming Language :: Python :: 3.11
Classifier: Programming Language :: Python :: 3.12
Requires-Dist: tomli-w (>=1.0.0,<2.0.0)
Requires-Dist: tomlkit (>=0.12.3,<0.13.0)
